baselinker/__init__.py
baselinker/client.py
baselinker/exceptions.py
baselinker/modules/__init__.py
baselinker/modules/base.py
baselinker/modules/courier.py
baselinker/modules/devices.py
baselinker/modules/documents.py
baselinker/modules/external_storage.py
baselinker/modules/inventory.py
baselinker/modules/invoices.py
baselinker/modules/orders.py
baselinker/modules/products.py
baselinker/modules/returns.py
baselinker/utils/__init__.py
baselinker/utils/validators.py
baselinker_api-1.0.0.dist-info/METADATA
baselinker_api-1.0.0.dist-info/WHEEL
baselinker_api-1.0.0.dist-info/licenses/LICENSE
baselinker_api-1.0.0.dist-info/RECORD
